repolist/__init__.py
repolist/cli.py
repolist/repolist.py
repolist-0.1.0.dist-info/entry_points.txt
repolist-0.1.0.dist-info/METADATA
repolist-0.1.0.dist-info/WHEEL
repolist-0.1.0.dist-info/RECORD
