Metadata-Version: 2.1
Name: repolist
Version: 0.1.0
Summary: Generate wordlists from Github repositories
Author: Adem Kouki
Author-email: ademkingnew@gmail.com
Requires-Python: >=3.9,<4.0
Classifier: Programming Language :: Python :: 3
Classifier: Programming Language :: Python :: 3.9
Classifier: Programming Language :: Python :: 3.10
Classifier: Programming Language :: Python :: 3.11
Classifier: Programming Language :: Python :: 3.12
Requires-Dist: argparse (>=1.4.0,<2.0.0)
Requires-Dist: colorama (>=0.4.6,<0.5.0)
Requires-Dist: requests (>=2.31.0,<3.0.0)
